{

    "allForms": [

        {
            "data": {
                "id" : "123",
                "formTitle": "Alpha_1",
                "formSubTitle": "Description 1",
                "index" : "1"
            }
        },

        {
            "data": {
                "id" : "434",
                "formTitle": "Alpha_2",
                "formSubTitle": "Description 2",
                "index" : "2"
            }
        },

        {
            "data": {
                "id" : "456",
                "formTitle": "Alpha_3",
                "formSubTitle": "Description 3",
                "index" : "3"
            }
        },

        {
            "data": {
                "id" : "5678",
                "formTitle": "Alpha_4",
                "formSubTitle": "Description 4",
                "index" : "4"
            }
        },

        {
            "data": {
                "id" : "96789",
                "formTitle": "Alpha_5",
                "formSubTitle": "Description 5",
                "index" : "5"
            }
        }



    ]

}
